onyx_client/__init__.py
onyx_client/authorizer/__init__.py
onyx_client/client.py
onyx_client/configuration/__init__.py
onyx_client/configuration/configuration.py
onyx_client/data/__init__.py
onyx_client/data/animation_keyframe.py
onyx_client/data/animation_value.py
onyx_client/data/boolean_value.py
onyx_client/data/date_information.py
onyx_client/data/device_command.py
onyx_client/data/device_mode.py
onyx_client/data/numeric_value.py
onyx_client/data/supported_versions.py
onyx_client/device/__init__.py
onyx_client/device/click.py
onyx_client/device/device.py
onyx_client/device/light.py
onyx_client/device/shutter.py
onyx_client/device/switch.py
onyx_client/device/weather.py
onyx_client/enum/__init__.py
onyx_client/enum/action.py
onyx_client/enum/device_type.py
onyx_client/exception/__init__.py
onyx_client/exception/invalid_command.py
onyx_client/exception/update_exception.py
onyx_client/group/__init__.py
onyx_client/group/group.py
onyx_client/helpers/__init__.py
onyx_client/helpers/url.py
onyx_client/utils/__init__.py
onyx_client/utils/const.py
onyx_client/utils/device_type.py
onyx_client/utils/filter.py
onyx_client/utils/mapper.py
onyx_client/utils/response.py
onyx_client-10.1.3.dist-info/METADATA
onyx_client-10.1.3.dist-info/WHEEL
onyx_client-10.1.3.dist-info/licenses/LICENSE
onyx_client-10.1.3.dist-info/RECORD
