Metadata-Version: 2.4
Name: onyx-client
Version: 10.1.3
Summary: HTTP Client for Hella's ONYX.CENTER API.
License: MIT
License-File: LICENSE
Keywords: hella-info,onyx,onyx-center
Author: Daniel Muehlbachler-Pietrzykowski
Author-email: daniel.muehlbachler@niftyside.io
Requires-Python: >=3.13,<3.15
Classifier: Development Status :: 5 - Production/Stable
Classifier: Intended Audience :: Developers
Classifier: License :: OSI Approved :: MIT License
Classifier: Operating System :: OS Independent
Classifier: Programming Language :: Python :: 3
Classifier: Programming Language :: Python :: 3.13
Classifier: Programming Language :: Python :: 3.14
Classifier: Topic :: Home Automation
Requires-Dist: aiohttp (>=3.8.5,<4.0.0)
Requires-Dist: asyncio (>=4.0.0,<5.0.0)
Project-URL: Repository, https://github.com/muhlba91/onyx-client
